mc_converter/CurseForge.py
mc_converter/Helpers/abstractions.py
mc_converter/Helpers/resourceAPI.py
mc_converter/Helpers/utils.py
mc_converter/Modrinth.py
mc_converter/MultiMC.py
mc_converter/__init__.py
mc_converter/main.py
mc_converter/packwiz.py
mc_converter-1.0.3.5.dist-info/entry_points.txt
mc_converter-1.0.3.5.dist-info/LICENSE
mc_converter-1.0.3.5.dist-info/WHEEL
mc_converter-1.0.3.5.dist-info/METADATA
mc_converter-1.0.3.5.dist-info/RECORD
